financepy/__init__.py
financepy/market/__init__.py
financepy/market/curves/__init__.py
financepy/market/curves/composite_discount_curve.py
financepy/market/curves/discount_curve.py
financepy/market/curves/discount_curve_flat.py
financepy/market/curves/discount_curve_ns.py
financepy/market/curves/discount_curve_nss.py
financepy/market/curves/discount_curve_poly.py
financepy/market/curves/discount_curve_pwf.py
financepy/market/curves/discount_curve_pwf_onf.py
financepy/market/curves/discount_curve_pwl.py
financepy/market/curves/discount_curve_zeros.py
financepy/market/curves/interpolator.py
financepy/market/prices/__init__.py
financepy/market/volatility/__init__.py
financepy/market/volatility/equity_vol_curve.py
financepy/market/volatility/equity_vol_surface.py
financepy/market/volatility/fx_vol_surface.py
financepy/market/volatility/fx_vol_surface_plus.py
financepy/market/volatility/ibor_cap_vol_curve.py
financepy/market/volatility/ibor_cap_vol_curve_fn.py
financepy/market/volatility/swaption_vol_surface.py
financepy/models/__init__.py
financepy/models/bachelier.py
financepy/models/bdt_tree.py
financepy/models/bk_tree.py
financepy/models/black.py
financepy/models/black_scholes.py
financepy/models/black_scholes_analytic.py
financepy/models/black_scholes_mc.py
financepy/models/black_scholes_mc_tests.py
financepy/models/black_shifted.py
financepy/models/cir_montecarlo.py
financepy/models/equity_barrier_models.py
financepy/models/equity_crr_tree.py
financepy/models/equity_lsmc.py
financepy/models/finite_difference.py
financepy/models/finite_difference_psor.py
financepy/models/gauss_copula.py
financepy/models/gauss_copula_lhp.py
financepy/models/gauss_copula_lhplus.py
financepy/models/gauss_copula_onefactor.py
financepy/models/gbm_process_simulator.py
financepy/models/heston.py
financepy/models/hw_tree.py
financepy/models/lmm_mc.py
financepy/models/loss_dbn_builder.py
financepy/models/merton_firm.py
financepy/models/merton_firm_mkt.py
financepy/models/model.py
financepy-1.0.1.dist-info/licenses/LICENSE
financepy-1.0.1.dist-info/METADATA
financepy-1.0.1.dist-info/WHEEL
financepy-1.0.1.dist-info/top_level.txt
financepy-1.0.1.dist-info/RECORD
