Metadata-Version: 2.4
Name: financepy
Version: 1.0.1
Summary: A Finance Securities Valuation Library
Home-page: https://github.com/domokane/FinancePy
Author: Dominic O'Kane
License: GPL-3.0-or-later
Project-URL: Source, https://github.com/domokane/FinancePy
Project-URL: Tracker, https://github.com/domokane/FinancePy/issues
Keywords: FINANCE,OPTIONS,BONDS,VALUATION,DERIVATIVES
Classifier: Development Status :: 4 - Beta
Classifier: Programming Language :: Python :: 3
Classifier: Operating System :: OS Independent
Requires-Python: >=3.8
License-File: LICENSE
Requires-Dist: numpy
Requires-Dist: scipy
Requires-Dist: numba
Requires-Dist: llvmlite
Provides-Extra: viz
Requires-Dist: matplotlib; extra == "viz"
Requires-Dist: pandas; extra == "viz"
Provides-Extra: dev
Requires-Dist: pytest; extra == "dev"
Requires-Dist: build; extra == "dev"
Requires-Dist: twine; extra == "dev"
Requires-Dist: ipython; extra == "dev"
Dynamic: author
Dynamic: classifier
Dynamic: description
Dynamic: description-content-type
Dynamic: home-page
Dynamic: keywords
Dynamic: license
Dynamic: license-file
Dynamic: project-url
Dynamic: provides-extra
Dynamic: requires-dist
Dynamic: requires-python
Dynamic: summary
